gotyno_validation/__init__.py
gotyno_validation/encoding.py
gotyno_validation/gotyno_output.py
gotyno_validation/notifications.py
gotyno_validation/validation.py
gotyno_validation/validation_test.py
gotyno_validation-0.0.7.dist-info/METADATA
gotyno_validation-0.0.7.dist-info/WHEEL
gotyno_validation-0.0.7.dist-info/top_level.txt
gotyno_validation-0.0.7.dist-info/RECORD
